examples/__init__.py
examples/example1.py
examples/example2.py
examples/example3.py
examples/example4.py
examples/example5.py
tests/__init__.py
tests/conftest.py
tests/test_fpt_operators.py
tests/test_fuzzy_transformer.py
tests/test_visuals.py
tests/test_visuals_ca.py
tests/test_zuffy.py
tests/test_zuffy_fit_iterator.py
zuffy/__init__.py
zuffy/_fpt_operators.py
zuffy/_visuals_color_assignment.py
zuffy/fuzzy_transformer.py
zuffy/util_dt.py
zuffy/visuals.py
zuffy/zuffy.py
zuffy/zuffy_datasets.py
zuffy/zuffy_fit_iterator.py
zuffy/utils/__init__.py
zuffy/utils/discovery.py
zuffy/utils/tests/__init__.py
zuffy/utils/tests/test_discovery.py
zuffy-0.5.dist-info/licenses/LICENSE
zuffy-0.5.dist-info/METADATA
zuffy-0.5.dist-info/WHEEL
zuffy-0.5.dist-info/top_level.txt
zuffy-0.5.dist-info/RECORD
