Metadata-Version: 2.4
Name: zuffy
Version: 0.5
Summary: Zuffy is a sklearn compatible open source python library that uses GP to induce Fuzzy Pattern Trees
Author: PXOM
Author-email: PXOM <zuffy@mahoonium.ie>
License-Expression: BSD-3-Clause
Project-URL: Homepage, https://github.com/pxom/zuffy
Project-URL: Issues, https://github.com/pxom/zuffy/issues
Classifier: Programming Language :: Python :: 3
Classifier: Operating System :: OS Independent
Requires-Python: >=3.8
License-File: LICENSE
Dynamic: author
Dynamic: license-file
